bugzilla2fedmsg_schema/__init__.py
bugzilla2fedmsg_schema/schema.py
bugzilla2fedmsg_schema/utils.py
bugzilla2fedmsg_schema-1.1.0.dist-info/LICENSE
bugzilla2fedmsg_schema-1.1.0.dist-info/METADATA
bugzilla2fedmsg_schema-1.1.0.dist-info/WHEEL
bugzilla2fedmsg_schema-1.1.0.dist-info/entry_points.txt
bugzilla2fedmsg_schema-1.1.0.dist-info/RECORD
