Metadata-Version: 2.1
Name: bugzilla2fedmsg-schema
Version: 1.1.0
Summary: Fedora Messaging schemas for bugzilla2fedmsg
Home-page: https://github.com/fedora-infra/bugzilla2fedmsg-schema
License: LGPL-2.1-or-later
Keywords: fedora-messaging
Author: Fedora Infrastructure
Author-email: infrastructure@lists.fedoraproject.org
Requires-Python: >=3.8.10,<4.0.0
Classifier: Development Status :: 5 - Production/Stable
Classifier: Intended Audience :: System Administrators
Classifier: License :: OSI Approved
Classifier: License :: OSI Approved :: GNU Lesser General Public License v2 or later (LGPLv2+)
Classifier: Operating System :: POSIX :: Linux
Classifier: Programming Language :: Python :: 3
Classifier: Programming Language :: Python :: 3.9
Classifier: Programming Language :: Python :: 3.10
Classifier: Programming Language :: Python :: 3.11
Classifier: Programming Language :: Python :: 3.12
Classifier: Programming Language :: Python :: 3.8
Classifier: Topic :: Communications
Classifier: Topic :: Software Development :: Libraries :: Python Modules
Requires-Dist: fedora-messaging (>=3.2.0,<4.0.0)
Project-URL: Repository, https://github.com/fedora-infra/bugzilla2fedmsg-schema.git
